zc.set-0.2-py3.8-nspkg.pth
zc/set/README.txt
zc/set/__init__.py
zc/set/tests.py
zc.set-0.2.dist-info/LICENSE.txt
zc.set-0.2.dist-info/METADATA
zc.set-0.2.dist-info/WHEEL
zc.set-0.2.dist-info/namespace_packages.txt
zc.set-0.2.dist-info/top_level.txt
zc.set-0.2.dist-info/RECORD
